{"kind":"Article","sha256":"b225242c35335858a0d9207ca5148162dffcb4dbea5f088f7247fc038ee5a240","slug":"details","location":"/details.md","dependencies":[],"frontmatter":{"title":"Tips, tricks, and potential gotchas","content_includes_title":false,"authors":[{"id":"Willie Aboumrad","name":"Willie Aboumrad"},{"id":"Sang Kim","name":"Sang Kim"}],"github":"https://github.com/willieab/ionq-skku-vision-challenge","subject":"Quantum Vision Challenge","venue":{"title":"IonQ-SKKU Hackathon"},"copyright":"IonQ, Inc (2024)","exports":[{"format":"md","filename":"details.md","url":"/qml-challenge-scorer/build/details-03aaa14dd57bc1ae4c0445548a59ba3b.md"}]},"mdast":{"type":"root","children":[{"type":"block","children":[{"type":"paragraph","position":{"start":{"line":4,"column":1},"end":{"line":4,"column":1}},"children":[{"type":"text","value":"Stick to the following recommendations to ensure smooth seas ahead.","position":{"start":{"line":4,"column":1},"end":{"line":4,"column":1}},"key":"WMpLz3nMoT"}],"key":"mr4yfVgt3J"},{"type":"admonition","kind":"important","children":[{"type":"admonitionTitle","children":[{"type":"text","value":"Important","key":"xdpcB2OwoG"}],"key":"ktIatZrA2E"},{"type":"paragraph","position":{"start":{"line":7,"column":1},"end":{"line":7,"column":1}},"children":[{"type":"text","value":"You’ll run the training loop on your local workstations. So part of the complexity of our challenge lies in choosing how to allocate your computational resources.","position":{"start":{"line":7,"column":1},"end":{"line":7,"column":1}},"key":"vrsGaULw1v"}],"key":"m9by7yzYJ7"},{"type":"paragraph","position":{"start":{"line":9,"column":1},"end":{"line":9,"column":1}},"children":[{"type":"text","value":"We recommend using at most ","position":{"start":{"line":9,"column":1},"end":{"line":9,"column":1}},"key":"jJ54Pl9mDm"},{"type":"text","value":"20","position":{"start":{"line":9,"column":1},"end":{"line":9,"column":1}},"key":"c8O1AqMvod"},{"type":"text","value":" qubits and no more than ","position":{"start":{"line":9,"column":1},"end":{"line":9,"column":1}},"key":"wlXbaHq5xD"},{"type":"text","value":"150","position":{"start":{"line":9,"column":1},"end":{"line":9,"column":1}},"key":"nFEOqvPQxS"},{"type":"text","value":" two-qubit gates and ","position":{"start":{"line":9,"column":1},"end":{"line":9,"column":1}},"key":"oU3Ri0eJv6"},{"type":"text","value":"60","position":{"start":{"line":9,"column":1},"end":{"line":9,"column":1}},"key":"p06iTm7Jcn"},{"type":"text","value":" parameters across your entire ","position":{"start":{"line":9,"column":1},"end":{"line":9,"column":1}},"key":"wwLJiOOp7j"},{"type":"crossReference","position":{"start":{"line":9,"column":1},"end":{"line":9,"column":1}},"children":[{"type":"text","value":"quantum layer","position":{"start":{"line":9,"column":1},"end":{"line":9,"column":1}},"key":"sXvHwLjyOo"}],"identifier":"sec-quantum-layer","label":"sec-quantum-layer","kind":"heading","template":"{name}","resolved":true,"html_id":"sec-quantum-layer","remote":true,"url":"/challenge-description","dataUrl":"/challenge-description.json","key":"yf9GtA0Jfx"},{"type":"text","value":". You’re free to choose the size of your local training and test sets.","position":{"start":{"line":9,"column":1},"end":{"line":9,"column":1}},"key":"rrprvRkMET"}],"key":"NyuMYC3ARo"},{"type":"paragraph","position":{"start":{"line":11,"column":1},"end":{"line":11,"column":1}},"children":[{"type":"text","value":"You’ll receive ","position":{"start":{"line":11,"column":1},"end":{"line":11,"column":1}},"key":"uNmyNxIObM"},{"type":"strong","position":{"start":{"line":11,"column":1},"end":{"line":11,"column":1}},"children":[{"type":"text","value":"bonus points","position":{"start":{"line":11,"column":1},"end":{"line":11,"column":1}},"key":"Q5HtZ6ZQYX"}],"key":"bbyj6cSSqa"},{"type":"text","value":" if you use fewer gates and parameters, and your accuracy score will be ","position":{"start":{"line":11,"column":1},"end":{"line":11,"column":1}},"key":"B0CFMu9Mkb"},{"type":"strong","position":{"start":{"line":11,"column":1},"end":{"line":11,"column":1}},"children":[{"type":"text","value":"penalized","position":{"start":{"line":11,"column":1},"end":{"line":11,"column":1}},"key":"hEgF1bNGlM"}],"key":"t1NeSxgzOs"},{"type":"text","value":" if you exceed these thresholds.","position":{"start":{"line":11,"column":1},"end":{"line":11,"column":1}},"key":"LuPFR6Uu2k"}],"key":"iWDBYQbgqG"}],"key":"TXV7Z7glaW"},{"type":"admonition","kind":"hint","children":[{"type":"admonitionTitle","children":[{"type":"text","value":"Tip","position":{"start":{"line":14,"column":1},"end":{"line":14,"column":1}},"key":"fqk7rVo42V"}],"key":"yVMkjpdhHp"},{"type":"paragraph","position":{"start":{"line":15,"column":1},"end":{"line":15,"column":1}},"children":[{"type":"text","value":"Use the ","position":{"start":{"line":15,"column":1},"end":{"line":15,"column":1}},"key":"SWZ2WrKZd3"},{"type":"inlineCode","value":"ionqvision","position":{"start":{"line":15,"column":1},"end":{"line":15,"column":1}},"key":"f28L2ICX7b"},{"type":"text","value":" package as-is: do ","position":{"start":{"line":15,"column":1},"end":{"line":15,"column":1}},"key":"PJEeRDbrom"},{"type":"strong","position":{"start":{"line":15,"column":1},"end":{"line":15,"column":1}},"children":[{"type":"text","value":"not","position":{"start":{"line":15,"column":1},"end":{"line":15,"column":1}},"key":"NNBzV9BANA"}],"key":"iIu4fzmd1e"},{"type":"text","value":" modify the source code files. You’re welcome to create new files and interact with the ","position":{"start":{"line":15,"column":1},"end":{"line":15,"column":1}},"key":"CZque5nwp9"},{"type":"inlineCode","value":"ionqvision","position":{"start":{"line":15,"column":1},"end":{"line":15,"column":1}},"key":"kHrNftfjGe"},{"type":"text","value":" modules through the ","position":{"start":{"line":15,"column":1},"end":{"line":15,"column":1}},"key":"DJUjSwrA6o"},{"type":"link","url":"https://willieab.github.io/qml-challenge-scorer/ionqvision-docs/","position":{"start":{"line":15,"column":1},"end":{"line":15,"column":1}},"children":[{"type":"text","value":"provided API","position":{"start":{"line":15,"column":1},"end":{"line":15,"column":1}},"key":"zNHasyizeu"}],"urlSource":"https://willieab.github.io/qml-challenge-scorer/ionqvision-docs/","key":"FodaYGYSGT"},{"type":"text","value":".","position":{"start":{"line":15,"column":1},"end":{"line":15,"column":1}},"key":"V8a4INVInH"}],"key":"cAymTUXmAG"},{"type":"paragraph","position":{"start":{"line":17,"column":1},"end":{"line":17,"column":1}},"children":[{"type":"text","value":"The auto-grader relies on the “source” distribution of the ","position":{"start":{"line":17,"column":1},"end":{"line":17,"column":1}},"key":"kNXcNqBAi8"},{"type":"inlineCode","value":"ionqvision","position":{"start":{"line":17,"column":1},"end":{"line":17,"column":1}},"key":"ig7p7jpkJJ"},{"type":"text","value":" package, so any of your local changes will ","position":{"start":{"line":17,"column":1},"end":{"line":17,"column":1}},"key":"ainFzKeGAz"},{"type":"strong","position":{"start":{"line":17,"column":1},"end":{"line":17,"column":1}},"children":[{"type":"text","value":"not","position":{"start":{"line":17,"column":1},"end":{"line":17,"column":1}},"key":"mRIvbTAFZB"}],"key":"f9zAEcdSDC"},{"type":"text","value":" be considered in the evaluation stage.","position":{"start":{"line":17,"column":1},"end":{"line":17,"column":1}},"key":"i1y2JzAwtD"}],"key":"YNLawvHTWv"}],"key":"ZiuSGJvf8L"},{"type":"admonition","kind":"hint","children":[{"type":"admonitionTitle","children":[{"type":"text","value":"Tip","position":{"start":{"line":20,"column":1},"end":{"line":20,"column":1}},"key":"KsfOr7rq7C"}],"key":"F6ogLe2AL8"},{"type":"paragraph","position":{"start":{"line":21,"column":1},"end":{"line":21,"column":1}},"children":[{"type":"text","value":"The classical part of the structure of our quantum-classical neural network is ","position":{"start":{"line":21,"column":1},"end":{"line":21,"column":1}},"key":"TvRggM51v1"},{"type":"strong","position":{"start":{"line":21,"column":1},"end":{"line":21,"column":1}},"children":[{"type":"text","value":"fixed","position":{"start":{"line":21,"column":1},"end":{"line":21,"column":1}},"key":"m2Lw2pDIDY"}],"key":"xxOBxm8tdq"},{"type":"text","value":"; focus on developing the best possible ","position":{"start":{"line":21,"column":1},"end":{"line":21,"column":1}},"key":"VVOVDsyGLd"},{"type":"crossReference","position":{"start":{"line":21,"column":1},"end":{"line":21,"column":1}},"children":[{"type":"text","value":"quantum layer","position":{"start":{"line":21,"column":1},"end":{"line":21,"column":1}},"key":"K6fJ7PTEZ2"}],"identifier":"sec-quantum-layer","label":"sec-quantum-layer","kind":"heading","template":"{name}","resolved":true,"html_id":"sec-quantum-layer","remote":true,"url":"/challenge-description","dataUrl":"/challenge-description.json","key":"frtDr9BS7G"},{"type":"text","value":".","position":{"start":{"line":21,"column":1},"end":{"line":21,"column":1}},"key":"D3G0pbaGsR"}],"key":"jhzxI5BShu"}],"key":"yTZD4HLqGH"},{"type":"admonition","kind":"caution","children":[{"type":"admonitionTitle","children":[{"type":"text","value":"Caution","key":"IeJRxJIby4"}],"key":"qpGIQwpB3r"},{"type":"paragraph","position":{"start":{"line":25,"column":1},"end":{"line":25,"column":1}},"children":[{"type":"text","value":"The backward pass of the training loop uses a ","position":{"start":{"line":25,"column":1},"end":{"line":25,"column":1}},"key":"QaUZIOS2Bb"},{"type":"link","url":"https://sakhujasaiyam.medium.com/parameter-shift-rule-for-finding-gradients-in-quantum-circuits-9d61957fc1c4","position":{"start":{"line":25,"column":1},"end":{"line":25,"column":1}},"children":[{"type":"text","value":"parameter-shift rule","position":{"start":{"line":25,"column":1},"end":{"line":25,"column":1}},"key":"JieIuwzFRU"}],"urlSource":"https://sakhujasaiyam.medium.com/parameter-shift-rule-for-finding-gradients-in-quantum-circuits-9d61957fc1c4","key":"LnO14IqBH6"},{"type":"text","value":" to differentiate your encoder and ansatz with respect to the input data and the trainable parameters.","position":{"start":{"line":25,"column":1},"end":{"line":25,"column":1}},"key":"Ppjz5p7OAU"}],"key":"iFNvUifQhU"},{"type":"paragraph","position":{"start":{"line":27,"column":1},"end":{"line":27,"column":1}},"children":[{"type":"text","value":"Make sure your ansatz design remains differentiable; for more details, check out the ","position":{"start":{"line":27,"column":1},"end":{"line":27,"column":1}},"key":"UGkQWgE41v"},{"type":"inlineCode","value":"ionqvision.ansatze.VariationalAnsatz","position":{"start":{"line":27,"column":1},"end":{"line":27,"column":1}},"key":"qKu1lSeyb8"},{"type":"text","value":" ","position":{"start":{"line":27,"column":1},"end":{"line":27,"column":1}},"key":"pf7PYXsJB7"},{"type":"link","url":"https://willieab.github.io/qml-challenge-scorer/ionqvision-docs/ansatze.html","position":{"start":{"line":27,"column":1},"end":{"line":27,"column":1}},"children":[{"type":"text","value":"documentation","position":{"start":{"line":27,"column":1},"end":{"line":27,"column":1}},"key":"JS9CwewhEK"}],"urlSource":"https://willieab.github.io/qml-challenge-scorer/ionqvision-docs/ansatze.html","key":"QYlNXHESDC"},{"type":"text","value":".","position":{"start":{"line":27,"column":1},"end":{"line":27,"column":1}},"key":"qKEWiKDGjQ"}],"key":"oBFyhuGNLt"}],"key":"ctJ1WOhUQI"},{"type":"admonition","kind":"hint","children":[{"type":"admonitionTitle","children":[{"type":"text","value":"Tip","position":{"start":{"line":30,"column":1},"end":{"line":30,"column":1}},"key":"BOUAuWXzCb"}],"key":"P1T2PUHF4z"},{"type":"paragraph","position":{"start":{"line":31,"column":1},"end":{"line":31,"column":1}},"children":[{"type":"text","value":"Feel free to fire up a Jupyter notebook to hack on the starter code and implement your own encoder and ansatz. Ensure that Jupyter is running the appropriate kernel. For instance, you can install ","position":{"start":{"line":31,"column":1},"end":{"line":31,"column":1}},"key":"ahr15uV8ek"},{"type":"inlineCode","value":"jupyterlab","position":{"start":{"line":31,"column":1},"end":{"line":31,"column":1}},"key":"qAotZwsP54"},{"type":"text","value":" in your virtual environment and then launch it as follows.","position":{"start":{"line":31,"column":1},"end":{"line":31,"column":1}},"key":"consIbsO4H"}],"key":"KeGcnRI3Cv"},{"type":"code","lang":"bash","value":"source .venv/bin/activate\npip install jupyterlab\nsource .venv/bin/activate\njupyter-lab","key":"TzJrII8PXJ"},{"type":"paragraph","position":{"start":{"line":40,"column":1},"end":{"line":40,"column":1}},"children":[{"type":"text","value":"Or stick to ","position":{"start":{"line":40,"column":1},"end":{"line":40,"column":1}},"key":"Gtc1sH8q0L"},{"type":"inlineCode","value":".py","position":{"start":{"line":40,"column":1},"end":{"line":40,"column":1}},"key":"WzMVa6LVNh"},{"type":"text","value":" scripts. The choice is yours.","position":{"start":{"line":40,"column":1},"end":{"line":40,"column":1}},"key":"F4I4Uwjakq"}],"key":"BcrfeIlRua"}],"key":"EmROm8oIQa"},{"type":"admonition","kind":"warning","children":[{"type":"admonitionTitle","children":[{"type":"text","value":"Warning","key":"TlwDOI0uHR"}],"key":"ox3VN3TCtR"},{"type":"paragraph","position":{"start":{"line":44,"column":1},"end":{"line":44,"column":1}},"children":[{"type":"text","value":"The starter code assumes your current directory is set as the ","position":{"start":{"line":44,"column":1},"end":{"line":44,"column":1}},"key":"zpqyErDIPR"},{"type":"strong","position":{"start":{"line":44,"column":1},"end":{"line":44,"column":1}},"children":[{"type":"text","value":"root","position":{"start":{"line":44,"column":1},"end":{"line":44,"column":1}},"key":"qd0GuhxTUn"}],"key":"kCwy41Zunn"},{"type":"text","value":" level (","position":{"start":{"line":44,"column":1},"end":{"line":44,"column":1}},"key":"GiR7M1cYI4"},{"type":"inlineCode","value":"ionq-skku-vision-challenge","position":{"start":{"line":44,"column":1},"end":{"line":44,"column":1}},"key":"NqSKQbLftB"},{"type":"text","value":") of the cloned challenge repository.","position":{"start":{"line":44,"column":1},"end":{"line":44,"column":1}},"key":"Tmv7jNrO7m"}],"key":"jkIHP0RjKI"},{"type":"paragraph","position":{"start":{"line":46,"column":1},"end":{"line":46,"column":1}},"children":[{"type":"text","value":"If you’re working in a different directory, be sure to modify the commands given here and use the ","position":{"start":{"line":46,"column":1},"end":{"line":46,"column":1}},"key":"HXxvEhX9pN"},{"type":"inlineCode","value":"path_to_repo","position":{"start":{"line":46,"column":1},"end":{"line":46,"column":1}},"key":"iEPnb28D9G"},{"type":"text","value":" argument appropriately.","position":{"start":{"line":46,"column":1},"end":{"line":46,"column":1}},"key":"uM9yNneKJR"}],"key":"C0m9U1o17O"}],"key":"xXSVD7IVpS"},{"type":"admonition","kind":"danger","children":[{"type":"admonitionTitle","children":[{"type":"text","value":"Danger","key":"SMqGUlKVCV"}],"key":"LKzSE6dbDX"},{"type":"paragraph","position":{"start":{"line":51,"column":1},"end":{"line":51,"column":1}},"children":[{"type":"text","value":"Be sure to set up a branch for your team in your clone of the the challenge repository, as explained in our ","position":{"start":{"line":51,"column":1},"end":{"line":51,"column":1}},"key":"bJmJt2iMzb"},{"type":"link","position":{"start":{"line":51,"column":1},"end":{"line":51,"column":1}},"children":[{"type":"text","value":"setup instructions","position":{"start":{"line":51,"column":1},"end":{"line":51,"column":1}},"key":"PnFu7GEpMC"}],"identifier":"ch-env-setup","label":"ch-env-setup","url":"/env-setup","internal":true,"dataUrl":"/env-setup.json","key":"Uo738bfriK"},{"type":"text","value":". Your branch’s name will be used to identify your team in the leader board, so choose a unique name. The auto-grader assumes you’ve used “-” to separate words in your team name.","position":{"start":{"line":51,"column":1},"end":{"line":51,"column":1}},"key":"kcj5Ma0nVk"}],"key":"zHsWrl9NIa"},{"type":"paragraph","position":{"start":{"line":53,"column":1},"end":{"line":53,"column":1}},"children":[{"type":"text","value":"For instance, if your team is named ","position":{"start":{"line":53,"column":1},"end":{"line":53,"column":1}},"key":"UEBM8AUXQA"},{"type":"inlineCode","value":"Best Quantum Hackers","position":{"start":{"line":53,"column":1},"end":{"line":53,"column":1}},"key":"BAiESBkZzy"},{"type":"text","value":", you should set up your branch with the following command after cloning the challenge repo.","position":{"start":{"line":53,"column":1},"end":{"line":53,"column":1}},"key":"nzNzMo0V4a"}],"key":"Qt84X2I7Cc"},{"type":"code","lang":"bash","value":"git checkout -b best-quantum-hackers","key":"lbgFBDTdfl"}],"identifier":"block-team-branch","label":"block-team-branch","html_id":"block-team-branch","key":"kFHfn9d4qi"}],"key":"w7WAx3WQSm"}],"key":"e7qIsXFgon"},"references":{"cite":{"order":[],"data":{}}},"footer":{"navigation":{"prev":{"title":"Your mission","url":"/challenge-description","group":"Zero or one?"},"next":{"title":"Environment set up","url":"/env-setup","group":"Zero or one?"}}},"domain":"http://localhost:3000"}