{"kind":"Article","sha256":"b225242c35335858a0d9207ca5148162dffcb4dbea5f088f7247fc038ee5a240","slug":"details","location":"/details.md","dependencies":[],"frontmatter":{"title":"Tips, tricks, and potential gotchas","content_includes_title":false,"authors":[{"id":"Willie Aboumrad","name":"Willie Aboumrad"},{"id":"Sang Kim","name":"Sang Kim"}],"github":"https://github.com/willieab/ionq-skku-vision-challenge","subject":"Quantum Vision Challenge","venue":{"title":"IonQ-SKKU Hackathon"},"copyright":"IonQ, Inc (2024)","exports":[{"format":"md","filename":"details.md","url":"/qml-challenge-scorer/build/details-0299839cab97bc36bf979fba77df4958.md"}]},"mdast":{"type":"root","children":[{"type":"block","children":[{"type":"paragraph","position":{"start":{"line":4,"column":1},"end":{"line":4,"column":1}},"children":[{"type":"text","value":"Stick to the following recommendations to ensure smooth seas ahead.","position":{"start":{"line":4,"column":1},"end":{"line":4,"column":1}},"key":"stmEf7YI2n"}],"key":"Nw1LPkcMrR"},{"type":"admonition","kind":"important","children":[{"type":"admonitionTitle","children":[{"type":"text","value":"Important","key":"nHynhDcai9"}],"key":"JcHmQTOXcc"},{"type":"paragraph","position":{"start":{"line":7,"column":1},"end":{"line":7,"column":1}},"children":[{"type":"text","value":"You’ll run the training loop on your local workstations. So part of the complexity of our challenge lies in choosing how to allocate your computational resources.","position":{"start":{"line":7,"column":1},"end":{"line":7,"column":1}},"key":"GRiCrmiNJB"}],"key":"KSSoyEXCmt"},{"type":"paragraph","position":{"start":{"line":9,"column":1},"end":{"line":9,"column":1}},"children":[{"type":"text","value":"We recommend using at most ","position":{"start":{"line":9,"column":1},"end":{"line":9,"column":1}},"key":"x1AoNJlLJN"},{"type":"text","value":"20","position":{"start":{"line":9,"column":1},"end":{"line":9,"column":1}},"key":"t7UjckYDCB"},{"type":"text","value":" qubits and no more than ","position":{"start":{"line":9,"column":1},"end":{"line":9,"column":1}},"key":"useGPFGU6y"},{"type":"text","value":"150","position":{"start":{"line":9,"column":1},"end":{"line":9,"column":1}},"key":"oSapQ6wa3B"},{"type":"text","value":" two-qubit gates and ","position":{"start":{"line":9,"column":1},"end":{"line":9,"column":1}},"key":"mTYaHr7NSa"},{"type":"text","value":"60","position":{"start":{"line":9,"column":1},"end":{"line":9,"column":1}},"key":"vVBjpqPulG"},{"type":"text","value":" parameters across your entire ","position":{"start":{"line":9,"column":1},"end":{"line":9,"column":1}},"key":"Djnp5Mo4n7"},{"type":"crossReference","position":{"start":{"line":9,"column":1},"end":{"line":9,"column":1}},"children":[{"type":"text","value":"quantum layer","position":{"start":{"line":9,"column":1},"end":{"line":9,"column":1}},"key":"VK7XpQ8X0E"}],"identifier":"sec-quantum-layer","label":"sec-quantum-layer","kind":"heading","template":"{name}","resolved":true,"html_id":"sec-quantum-layer","remote":true,"url":"/challenge-description","dataUrl":"/challenge-description.json","key":"hFV0Fc94xY"},{"type":"text","value":". You’re free to choose the size of your local training and test sets.","position":{"start":{"line":9,"column":1},"end":{"line":9,"column":1}},"key":"NEC0WAogdI"}],"key":"HHD0FG9rJx"},{"type":"paragraph","position":{"start":{"line":11,"column":1},"end":{"line":11,"column":1}},"children":[{"type":"text","value":"You’ll receive ","position":{"start":{"line":11,"column":1},"end":{"line":11,"column":1}},"key":"Kpl7F6v4II"},{"type":"strong","position":{"start":{"line":11,"column":1},"end":{"line":11,"column":1}},"children":[{"type":"text","value":"bonus points","position":{"start":{"line":11,"column":1},"end":{"line":11,"column":1}},"key":"xAdniT2eYp"}],"key":"bZBH3yuPbj"},{"type":"text","value":" if you use fewer gates and parameters, and your accuracy score will be ","position":{"start":{"line":11,"column":1},"end":{"line":11,"column":1}},"key":"T48ZHYRJnM"},{"type":"strong","position":{"start":{"line":11,"column":1},"end":{"line":11,"column":1}},"children":[{"type":"text","value":"penalized","position":{"start":{"line":11,"column":1},"end":{"line":11,"column":1}},"key":"Zhw6n2CKML"}],"key":"y3wNHELXsl"},{"type":"text","value":" if you exceed these thresholds.","position":{"start":{"line":11,"column":1},"end":{"line":11,"column":1}},"key":"piwr4aDPt2"}],"key":"l6wS8U7gvj"}],"key":"vTbkbrN0he"},{"type":"admonition","kind":"hint","children":[{"type":"admonitionTitle","children":[{"type":"text","value":"Tip","position":{"start":{"line":14,"column":1},"end":{"line":14,"column":1}},"key":"IypmQz7Xu7"}],"key":"QgkUwsQ63i"},{"type":"paragraph","position":{"start":{"line":15,"column":1},"end":{"line":15,"column":1}},"children":[{"type":"text","value":"Use the ","position":{"start":{"line":15,"column":1},"end":{"line":15,"column":1}},"key":"OhXrBo3U3U"},{"type":"inlineCode","value":"ionqvision","position":{"start":{"line":15,"column":1},"end":{"line":15,"column":1}},"key":"qibJWEB9g3"},{"type":"text","value":" package as-is: do ","position":{"start":{"line":15,"column":1},"end":{"line":15,"column":1}},"key":"cnFZ1nN5iS"},{"type":"strong","position":{"start":{"line":15,"column":1},"end":{"line":15,"column":1}},"children":[{"type":"text","value":"not","position":{"start":{"line":15,"column":1},"end":{"line":15,"column":1}},"key":"hV84oQGXhI"}],"key":"oilsHiBTCM"},{"type":"text","value":" modify the source code files. You’re welcome to create new files and interact with the ","position":{"start":{"line":15,"column":1},"end":{"line":15,"column":1}},"key":"VESfJBkMZ4"},{"type":"inlineCode","value":"ionqvision","position":{"start":{"line":15,"column":1},"end":{"line":15,"column":1}},"key":"pR44xjMlAn"},{"type":"text","value":" modules through the ","position":{"start":{"line":15,"column":1},"end":{"line":15,"column":1}},"key":"C0uhi7NZ3T"},{"type":"link","url":"https://willieab.github.io/qml-challenge-scorer/ionqvision-docs/","position":{"start":{"line":15,"column":1},"end":{"line":15,"column":1}},"children":[{"type":"text","value":"provided API","position":{"start":{"line":15,"column":1},"end":{"line":15,"column":1}},"key":"WrencwYdiP"}],"urlSource":"https://willieab.github.io/qml-challenge-scorer/ionqvision-docs/","key":"TWdN05kRRF"},{"type":"text","value":".","position":{"start":{"line":15,"column":1},"end":{"line":15,"column":1}},"key":"E0YqVVCpAC"}],"key":"DP3CoebHRm"},{"type":"paragraph","position":{"start":{"line":17,"column":1},"end":{"line":17,"column":1}},"children":[{"type":"text","value":"The auto-grader relies on the “source” distribution of the ","position":{"start":{"line":17,"column":1},"end":{"line":17,"column":1}},"key":"sPh3hd0HRM"},{"type":"inlineCode","value":"ionqvision","position":{"start":{"line":17,"column":1},"end":{"line":17,"column":1}},"key":"vu4cwOVGwF"},{"type":"text","value":" package, so any of your local changes will ","position":{"start":{"line":17,"column":1},"end":{"line":17,"column":1}},"key":"SAvY6dKrss"},{"type":"strong","position":{"start":{"line":17,"column":1},"end":{"line":17,"column":1}},"children":[{"type":"text","value":"not","position":{"start":{"line":17,"column":1},"end":{"line":17,"column":1}},"key":"NMRlUdTxmw"}],"key":"SlDEJgbQI1"},{"type":"text","value":" be considered in the evaluation stage.","position":{"start":{"line":17,"column":1},"end":{"line":17,"column":1}},"key":"RQrCE5LWQj"}],"key":"VXcJMT7RrU"}],"key":"pYPgVdyUzL"},{"type":"admonition","kind":"hint","children":[{"type":"admonitionTitle","children":[{"type":"text","value":"Tip","position":{"start":{"line":20,"column":1},"end":{"line":20,"column":1}},"key":"wupPehBsGL"}],"key":"xe9gqLGeqO"},{"type":"paragraph","position":{"start":{"line":21,"column":1},"end":{"line":21,"column":1}},"children":[{"type":"text","value":"The classical part of the structure of our quantum-classical neural network is ","position":{"start":{"line":21,"column":1},"end":{"line":21,"column":1}},"key":"El6ZTawDJc"},{"type":"strong","position":{"start":{"line":21,"column":1},"end":{"line":21,"column":1}},"children":[{"type":"text","value":"fixed","position":{"start":{"line":21,"column":1},"end":{"line":21,"column":1}},"key":"LfMey4HUlY"}],"key":"iKGRVFMP7d"},{"type":"text","value":"; focus on developing the best possible ","position":{"start":{"line":21,"column":1},"end":{"line":21,"column":1}},"key":"HAR6pWOWUR"},{"type":"crossReference","position":{"start":{"line":21,"column":1},"end":{"line":21,"column":1}},"children":[{"type":"text","value":"quantum layer","position":{"start":{"line":21,"column":1},"end":{"line":21,"column":1}},"key":"dGdSmEXIIo"}],"identifier":"sec-quantum-layer","label":"sec-quantum-layer","kind":"heading","template":"{name}","resolved":true,"html_id":"sec-quantum-layer","remote":true,"url":"/challenge-description","dataUrl":"/challenge-description.json","key":"FdFxZbAij3"},{"type":"text","value":".","position":{"start":{"line":21,"column":1},"end":{"line":21,"column":1}},"key":"QMXQzQCvPr"}],"key":"UOm54zLSlx"}],"key":"We0Z9N2mFu"},{"type":"admonition","kind":"caution","children":[{"type":"admonitionTitle","children":[{"type":"text","value":"Caution","key":"zXZ8c8YpwA"}],"key":"jTp8gZXq4a"},{"type":"paragraph","position":{"start":{"line":25,"column":1},"end":{"line":25,"column":1}},"children":[{"type":"text","value":"The backward pass of the training loop uses a ","position":{"start":{"line":25,"column":1},"end":{"line":25,"column":1}},"key":"gWdli2o2Ql"},{"type":"link","url":"https://sakhujasaiyam.medium.com/parameter-shift-rule-for-finding-gradients-in-quantum-circuits-9d61957fc1c4","position":{"start":{"line":25,"column":1},"end":{"line":25,"column":1}},"children":[{"type":"text","value":"parameter-shift rule","position":{"start":{"line":25,"column":1},"end":{"line":25,"column":1}},"key":"sTJLeho7dc"}],"urlSource":"https://sakhujasaiyam.medium.com/parameter-shift-rule-for-finding-gradients-in-quantum-circuits-9d61957fc1c4","key":"bfTt7aQ8vU"},{"type":"text","value":" to differentiate your encoder and ansatz with respect to the input data and the trainable parameters.","position":{"start":{"line":25,"column":1},"end":{"line":25,"column":1}},"key":"dqUC1SFgPW"}],"key":"m2h7HcYCWw"},{"type":"paragraph","position":{"start":{"line":27,"column":1},"end":{"line":27,"column":1}},"children":[{"type":"text","value":"Make sure your ansatz design remains differentiable; for more details, check out the ","position":{"start":{"line":27,"column":1},"end":{"line":27,"column":1}},"key":"zmPNmmlPI5"},{"type":"inlineCode","value":"ionqvision.ansatze.VariationalAnsatz","position":{"start":{"line":27,"column":1},"end":{"line":27,"column":1}},"key":"RhKkFbDpGs"},{"type":"text","value":" ","position":{"start":{"line":27,"column":1},"end":{"line":27,"column":1}},"key":"lZjMp25Yqt"},{"type":"link","url":"https://willieab.github.io/qml-challenge-scorer/ionqvision-docs/ansatze.html","position":{"start":{"line":27,"column":1},"end":{"line":27,"column":1}},"children":[{"type":"text","value":"documentation","position":{"start":{"line":27,"column":1},"end":{"line":27,"column":1}},"key":"R0LXjoEFU7"}],"urlSource":"https://willieab.github.io/qml-challenge-scorer/ionqvision-docs/ansatze.html","key":"LQDVRPKDgM"},{"type":"text","value":".","position":{"start":{"line":27,"column":1},"end":{"line":27,"column":1}},"key":"fyO56AXfN1"}],"key":"Skd0hX6zz0"}],"key":"X4JpXnM5Wz"},{"type":"admonition","kind":"hint","children":[{"type":"admonitionTitle","children":[{"type":"text","value":"Tip","position":{"start":{"line":30,"column":1},"end":{"line":30,"column":1}},"key":"V14JFuptaf"}],"key":"nbbaeVlSok"},{"type":"paragraph","position":{"start":{"line":31,"column":1},"end":{"line":31,"column":1}},"children":[{"type":"text","value":"Feel free to fire up a Jupyter notebook to hack on the starter code and implement your own encoder and ansatz. Ensure that Jupyter is running the appropriate kernel. For instance, you can install ","position":{"start":{"line":31,"column":1},"end":{"line":31,"column":1}},"key":"ni93iKvKsQ"},{"type":"inlineCode","value":"jupyterlab","position":{"start":{"line":31,"column":1},"end":{"line":31,"column":1}},"key":"rkLZXskR8e"},{"type":"text","value":" in your virtual environment and then launch it as follows.","position":{"start":{"line":31,"column":1},"end":{"line":31,"column":1}},"key":"jnU30VcQoA"}],"key":"RtAdkzM3Yg"},{"type":"code","lang":"bash","value":"source .venv/bin/activate\npip install jupyterlab\nsource .venv/bin/activate\njupyter-lab","key":"yYb1CNSjM9"},{"type":"paragraph","position":{"start":{"line":40,"column":1},"end":{"line":40,"column":1}},"children":[{"type":"text","value":"Or stick to ","position":{"start":{"line":40,"column":1},"end":{"line":40,"column":1}},"key":"iidklk0LKb"},{"type":"inlineCode","value":".py","position":{"start":{"line":40,"column":1},"end":{"line":40,"column":1}},"key":"EFxjwYpm82"},{"type":"text","value":" scripts. The choice is yours.","position":{"start":{"line":40,"column":1},"end":{"line":40,"column":1}},"key":"gn4CRh9lXM"}],"key":"Hngbx760dH"}],"key":"VHTsTFm1i4"},{"type":"admonition","kind":"warning","children":[{"type":"admonitionTitle","children":[{"type":"text","value":"Warning","key":"FyghVVJBqv"}],"key":"asRRFVQ6su"},{"type":"paragraph","position":{"start":{"line":44,"column":1},"end":{"line":44,"column":1}},"children":[{"type":"text","value":"The starter code assumes your current directory is set as the ","position":{"start":{"line":44,"column":1},"end":{"line":44,"column":1}},"key":"nrbtuMlN6B"},{"type":"strong","position":{"start":{"line":44,"column":1},"end":{"line":44,"column":1}},"children":[{"type":"text","value":"root","position":{"start":{"line":44,"column":1},"end":{"line":44,"column":1}},"key":"kzkvGtvQZy"}],"key":"ASeU7abWxm"},{"type":"text","value":" level (","position":{"start":{"line":44,"column":1},"end":{"line":44,"column":1}},"key":"C0CVUlSCi6"},{"type":"inlineCode","value":"ionq-skku-vision-challenge","position":{"start":{"line":44,"column":1},"end":{"line":44,"column":1}},"key":"pzMPPmvV9W"},{"type":"text","value":") of the cloned challenge repository.","position":{"start":{"line":44,"column":1},"end":{"line":44,"column":1}},"key":"Kvmna2iUNE"}],"key":"zXnTlAlhsw"},{"type":"paragraph","position":{"start":{"line":46,"column":1},"end":{"line":46,"column":1}},"children":[{"type":"text","value":"If you’re working in a different directory, be sure to modify the commands given here and use the ","position":{"start":{"line":46,"column":1},"end":{"line":46,"column":1}},"key":"Ogth2Iu325"},{"type":"inlineCode","value":"path_to_repo","position":{"start":{"line":46,"column":1},"end":{"line":46,"column":1}},"key":"aJwnVWiLF5"},{"type":"text","value":" argument appropriately.","position":{"start":{"line":46,"column":1},"end":{"line":46,"column":1}},"key":"r9hDIlna9G"}],"key":"Io3H4xEFSB"}],"key":"YajQk2yniQ"},{"type":"admonition","kind":"danger","children":[{"type":"admonitionTitle","children":[{"type":"text","value":"Danger","key":"i9Mt0xapn4"}],"key":"Rxp9a4pPxL"},{"type":"paragraph","position":{"start":{"line":51,"column":1},"end":{"line":51,"column":1}},"children":[{"type":"text","value":"Be sure to set up a branch for your team in your clone of the the challenge repository, as explained in our ","position":{"start":{"line":51,"column":1},"end":{"line":51,"column":1}},"key":"yfLPmeDUdv"},{"type":"link","position":{"start":{"line":51,"column":1},"end":{"line":51,"column":1}},"children":[{"type":"text","value":"setup instructions","position":{"start":{"line":51,"column":1},"end":{"line":51,"column":1}},"key":"YyVYWRMk3u"}],"identifier":"ch-env-setup","label":"ch-env-setup","url":"/env-setup","internal":true,"dataUrl":"/env-setup.json","key":"L9UbgOemhW"},{"type":"text","value":". Your branch’s name will be used to identify your team in the leader board, so choose a unique name. The auto-grader assumes you’ve used “-” to separate words in your team name.","position":{"start":{"line":51,"column":1},"end":{"line":51,"column":1}},"key":"O22hOgpTvx"}],"key":"ofdFyP44dG"},{"type":"paragraph","position":{"start":{"line":53,"column":1},"end":{"line":53,"column":1}},"children":[{"type":"text","value":"For instance, if your team is named ","position":{"start":{"line":53,"column":1},"end":{"line":53,"column":1}},"key":"zU3xKtykPV"},{"type":"inlineCode","value":"Best Quantum Hackers","position":{"start":{"line":53,"column":1},"end":{"line":53,"column":1}},"key":"u6qgoSJznE"},{"type":"text","value":", you should set up your branch with the following command after cloning the challenge repo.","position":{"start":{"line":53,"column":1},"end":{"line":53,"column":1}},"key":"gYwykuONDI"}],"key":"txsFUwluX2"},{"type":"code","lang":"bash","value":"git checkout -b best-quantum-hackers","key":"Wg98pGk7ok"}],"identifier":"block-team-branch","label":"block-team-branch","html_id":"block-team-branch","key":"n28f3GPztU"}],"key":"W6vYc9AMI9"}],"key":"AFkWKSEKRt"},"references":{"cite":{"order":[],"data":{}}},"footer":{"navigation":{"prev":{"title":"Your mission","url":"/challenge-description","group":"Zero or one?"},"next":{"title":"Environment set up","url":"/env-setup","group":"Zero or one?"}}},"domain":"http://localhost:3000"}