{"kind":"Article","sha256":"96b40af01fa6c978ed5a702458217163ae730930e7271ae0f880de9821987185","slug":"env-setup","location":"/env_setup.md","dependencies":[],"frontmatter":{"title":"Environment set up","content_includes_title":false,"authors":[{"id":"Willie Aboumrad","name":"Willie Aboumrad"},{"id":"Sang Kim","name":"Sang Kim"}],"github":"https://github.com/willieab/ionq-skku-vision-challenge","subject":"Quantum Vision Challenge","venue":{"title":"IonQ-SKKU Hackathon"},"copyright":"IonQ, Inc (2024)","exports":[{"format":"md","filename":"env_setup.md","url":"/qml-challenge-scorer/build/env_setup-8de6a2ce0b81251cdb047fe3b2965f5d.md"}]},"mdast":{"type":"root","children":[{"type":"block","children":[{"type":"paragraph","position":{"start":{"line":4,"column":1},"end":{"line":4,"column":1}},"children":[{"type":"text","value":"To complete this challenge, you’ll need a local installation of ","position":{"start":{"line":4,"column":1},"end":{"line":4,"column":1}},"key":"nF0VserEJu"},{"type":"inlineCode","value":"ionqvision","position":{"start":{"line":4,"column":1},"end":{"line":4,"column":1}},"key":"GCcNNtx63c"},{"type":"text","value":". You can download the source files by ","position":{"start":{"line":4,"column":1},"end":{"line":4,"column":1}},"key":"t8RDzvpa0o"},{"type":"inlineCode","value":"git clone","position":{"start":{"line":4,"column":1},"end":{"line":4,"column":1}},"key":"xOvcHDAI2A"},{"type":"text","value":"-ing our ","position":{"start":{"line":4,"column":1},"end":{"line":4,"column":1}},"key":"Qdo58KeJbc"},{"type":"link","url":"https://github.com/willieab/ionq-skku-vision-challenge","position":{"start":{"line":4,"column":1},"end":{"line":4,"column":1}},"children":[{"type":"text","value":"challenge repository","position":{"start":{"line":4,"column":1},"end":{"line":4,"column":1}},"key":"zgBSAVWhIF"}],"urlSource":"https://github.com/willieab/ionq-skku-vision-challenge","error":true,"key":"IIfjaPWawo"},{"type":"text","value":", as follows.","position":{"start":{"line":4,"column":1},"end":{"line":4,"column":1}},"key":"GgPkgmOZeD"}],"key":"Fcap7psXlc"},{"type":"code","lang":"bash","value":"git clone https://github.com/willieab/ionq-skku-vision-challenge.git","key":"Ammb5AvkPg"},{"type":"paragraph","position":{"start":{"line":10,"column":1},"end":{"line":10,"column":1}},"children":[{"type":"text","value":"We recommend installing ","position":{"start":{"line":10,"column":1},"end":{"line":10,"column":1}},"key":"ohPfww2jYn"},{"type":"inlineCode","value":"ionqvision","position":{"start":{"line":10,"column":1},"end":{"line":10,"column":1}},"key":"oH7RQNRMgt"},{"type":"text","value":" in a virtual environment because it requires a number of dependencies, including minimum versions of ","position":{"start":{"line":10,"column":1},"end":{"line":10,"column":1}},"key":"SlajsOth43"},{"type":"inlineCode","value":"torch","position":{"start":{"line":10,"column":1},"end":{"line":10,"column":1}},"key":"kl8NWMHsUC"},{"type":"text","value":", ","position":{"start":{"line":10,"column":1},"end":{"line":10,"column":1}},"key":"aYhChaK3b3"},{"type":"inlineCode","value":"qiskit","position":{"start":{"line":10,"column":1},"end":{"line":10,"column":1}},"key":"ah3h0GBKEF"},{"type":"text","value":", and ","position":{"start":{"line":10,"column":1},"end":{"line":10,"column":1}},"key":"UaDCd0xRAC"},{"type":"inlineCode","value":"qiskit_ionq","position":{"start":{"line":10,"column":1},"end":{"line":10,"column":1}},"key":"dwEQNq1z4y"},{"type":"text","value":".","position":{"start":{"line":10,"column":1},"end":{"line":10,"column":1}},"key":"y2Qf2tZ68Y"}],"key":"GGkm1DoNI0"},{"type":"paragraph","position":{"start":{"line":12,"column":1},"end":{"line":12,"column":1}},"children":[{"type":"text","value":"The following code snippet illustrates a minimal installation on Unix/macOS. It creates a ","position":{"start":{"line":12,"column":1},"end":{"line":12,"column":1}},"key":"mZRxMOLoFk"},{"type":"link","url":"https://packaging.python.org/en/latest/guides/installing-using-pip-and-virtual-environments/","position":{"start":{"line":12,"column":1},"end":{"line":12,"column":1}},"children":[{"type":"text","value":"virtual environment using ","position":{"start":{"line":12,"column":1},"end":{"line":12,"column":1}},"key":"JnNkJiogiB"},{"type":"inlineCode","value":"venv","position":{"start":{"line":12,"column":1},"end":{"line":12,"column":1}},"key":"vJtxspP6DR"}],"urlSource":"https://packaging.python.org/en/latest/guides/installing-using-pip-and-virtual-environments/","key":"YZH9C8u53X"},{"type":"text","value":", activates it, and then installs ","position":{"start":{"line":12,"column":1},"end":{"line":12,"column":1}},"key":"d3DWrGNg3J"},{"type":"inlineCode","value":"ionqvision","position":{"start":{"line":12,"column":1},"end":{"line":12,"column":1}},"key":"akKmPnScf2"},{"type":"text","value":" using ","position":{"start":{"line":12,"column":1},"end":{"line":12,"column":1}},"key":"VGvvnTDlgx"},{"type":"inlineCode","value":"pip","position":{"start":{"line":12,"column":1},"end":{"line":12,"column":1}},"key":"DQeyDX4oDX"},{"type":"text","value":".","position":{"start":{"line":12,"column":1},"end":{"line":12,"column":1}},"key":"MZPIG0vvNa"}],"key":"SHqMdhVfk5"},{"type":"admonition","kind":"warning","children":[{"type":"admonitionTitle","children":[{"type":"text","value":"Warning","key":"Q7nulh2WR9"}],"key":"dP4m9Triue"},{"type":"paragraph","position":{"start":{"line":16,"column":1},"end":{"line":16,"column":1}},"children":[{"type":"text","value":"The following command assumes your current directory is the ","position":{"start":{"line":16,"column":1},"end":{"line":16,"column":1}},"key":"SaBuTVm3sj"},{"type":"strong","position":{"start":{"line":16,"column":1},"end":{"line":16,"column":1}},"children":[{"type":"text","value":"root","position":{"start":{"line":16,"column":1},"end":{"line":16,"column":1}},"key":"ZRHdPE0xLY"}],"key":"T8n3j60uuj"},{"type":"text","value":" level of the cloned challenge repository.","position":{"start":{"line":16,"column":1},"end":{"line":16,"column":1}},"key":"k0qM5N2sT8"}],"key":"QV2znjudTs"},{"type":"paragraph","position":{"start":{"line":18,"column":1},"end":{"line":18,"column":1}},"children":[{"type":"text","value":"It’s best practice to ","position":{"start":{"line":18,"column":1},"end":{"line":18,"column":1}},"key":"dPtGHi0G8r"},{"type":"strong","position":{"start":{"line":18,"column":1},"end":{"line":18,"column":1}},"children":[{"type":"text","value":".gitignore","position":{"start":{"line":18,"column":1},"end":{"line":18,"column":1}},"key":"pK08OlLcef"}],"key":"Qo2XIlthvc"},{"type":"text","value":" environment files. Running the following commands at the root level will avoid checking unnecessary files into GitHub.","position":{"start":{"line":18,"column":1},"end":{"line":18,"column":1}},"key":"PoguzylXIb"}],"key":"BKQ7GSGzmM"}],"key":"ZPkbNIweGu"},{"type":"code","lang":"bash","value":"python3 -m venv .venv\nsource .venv/bin/activate\npip install -e ionqvision","key":"oqhqvdsaus"},{"type":"paragraph","position":{"start":{"line":27,"column":1},"end":{"line":27,"column":1}},"children":[{"type":"text","value":"You could also use ","position":{"start":{"line":27,"column":1},"end":{"line":27,"column":1}},"key":"EibY1N9Fvy"},{"type":"link","url":"https://conda.io/projects/conda/en/latest/user-guide/install/index.html","position":{"start":{"line":27,"column":1},"end":{"line":27,"column":1}},"children":[{"type":"inlineCode","value":"conda","position":{"start":{"line":27,"column":1},"end":{"line":27,"column":1}},"key":"tloA2I4rc3"}],"urlSource":"https://conda.io/projects/conda/en/latest/user-guide/install/index.html","key":"SnShMLk5mj"},{"type":"text","value":" or any package manager to set up your development environment.","position":{"start":{"line":27,"column":1},"end":{"line":27,"column":1}},"key":"jsfPDihi4h"}],"key":"V2E04A0CeX"},{"type":"admonition","kind":"important","children":[{"type":"admonitionTitle","children":[{"type":"text","value":"Important","key":"xCCXWzuPnL"}],"key":"fRJTxTb28J"},{"type":"paragraph","position":{"start":{"line":30,"column":1},"end":{"line":30,"column":1}},"children":[{"type":"text","value":"You’ll submit trained models for grading by uploading certain artifacts to GitHub (see the ","position":{"start":{"line":30,"column":1},"end":{"line":30,"column":1}},"key":"E2N4sv0Lxn"},{"type":"inlineCode","value":"BinaryMNISTClassifier.submit_model_for_grading","position":{"start":{"line":30,"column":1},"end":{"line":30,"column":1}},"key":"l9szkgGByh"},{"type":"text","value":" method).","position":{"start":{"line":30,"column":1},"end":{"line":30,"column":1}},"key":"KnnlLi8gYh"}],"key":"kBr1qoVsID"},{"type":"paragraph","position":{"start":{"line":32,"column":1},"end":{"line":32,"column":1}},"children":[{"type":"text","value":"The ","position":{"start":{"line":32,"column":1},"end":{"line":32,"column":1}},"key":"fplKFyfZEY"},{"type":"inlineCode","value":"main","position":{"start":{"line":32,"column":1},"end":{"line":32,"column":1}},"key":"HSyaCA08k8"},{"type":"text","value":" branch is read-only, so you’ll need to push all your commits to a new branch. Create a new branch using your team name for identification by running the following command at the root level of your cloned repository.","position":{"start":{"line":32,"column":1},"end":{"line":32,"column":1}},"key":"dWKV0o1DXG"}],"key":"cuAFCWSGjR"},{"type":"admonition","kind":"danger","children":[{"type":"admonitionTitle","children":[{"type":"text","value":"Danger","key":"tHTlWvXQcr"}],"key":"LEwwQpHF0i"},{"type":"paragraph","position":{"start":{"line":36,"column":1},"end":{"line":36,"column":1}},"children":[{"type":"text","value":"Be sure to replace ","position":{"start":{"line":36,"column":1},"end":{"line":36,"column":1}},"key":"V7ZAicPqpW"},{"type":"inlineCode","value":"my-team-name","position":{"start":{"line":36,"column":1},"end":{"line":36,"column":1}},"key":"MalCGfrQEW"},{"type":"text","value":" in the next command with your team’s name!","position":{"start":{"line":36,"column":1},"end":{"line":36,"column":1}},"key":"bxE7A6NTIc"}],"key":"mzVekB2Eox"},{"type":"paragraph","position":{"start":{"line":38,"column":1},"end":{"line":38,"column":1}},"children":[{"type":"text","value":"This step is ","position":{"start":{"line":38,"column":1},"end":{"line":38,"column":1}},"key":"gQLQGxEnNR"},{"type":"strong","position":{"start":{"line":38,"column":1},"end":{"line":38,"column":1}},"children":[{"type":"text","value":"critical","position":{"start":{"line":38,"column":1},"end":{"line":38,"column":1}},"key":"QRkCrEeJAC"}],"key":"xaQH7Tk8lU"},{"type":"text","value":". We’ll use branch names to identify team submissions, so give your team a unique name!","position":{"start":{"line":38,"column":1},"end":{"line":38,"column":1}},"key":"PD0zFIGzo8"}],"key":"vZfl3lPfYy"}],"key":"nMZ9pwxzCF"},{"type":"code","lang":"bash","value":"git checkout -b my-team-name","key":"N5FjyHNqam"}],"key":"tiCWzkMFk5"}],"key":"pTaYLjQCsY"}],"key":"HsutReLtnh"},"references":{"cite":{"order":[],"data":{}}},"footer":{"navigation":{"prev":{"title":"Tips, tricks, and potential gotchas","url":"/details","group":"Zero or one?"},"next":{"title":"Leader board","url":"/leaderboard","group":"Zero or one?"}}},"domain":"http://localhost:3000"}